[
    {
        "name": "Manjalpur",
        "x1": false,
        "x2": false,
        "x3": false,
        "x4": false,
        "x5": false,
        "x6": false,
        "x7": false,
        "x8": false,
        "x9": false,
        "x10": false,
        "y1": false,
        "y2": false,
        "y3": false,
        "y4": false,
        "z1": false,
        "z2": false,
        "z3": false
    },
    {
        "name": "Gotri",
        "x1": false,
        "x2": false,
        "x3": false,
        "x4": false,
        "x5": false,
        "x6": false,
        "x7": false,
        "x8": false,
        "x9": false,
        "x10": false,
        "y1": false,
        "y2": false,
        "y3": false,
        "y4": false,
        "z1": false,
        "z2": false,
        "z3": false
    },
    {
        "name": "JP Road",
        "x1": false,
        "x2": false,
        "x3": false,
        "x4": false,
        "x5": false,
        "x6": false,
        "x7": false,
        "x8": false,
        "x9": false,
        "x10": false,
        "y1": false,
        "y2": false,
        "y3": false,
        "y4": false,
        "z1": false,
        "z2": false,
        "z3": false
    },
    {
        "name": "Sayajiganj",
        "x1": false,
        "x2": false,
        "x3": false,
        "x4": false,
        "x5": false,
        "x6": false,
        "x7": false,
        "x8": false,
        "x9": false,
        "x10": false,
        "y1": false,
        "y2": false,
        "y3": false,
        "y4": false,
        "z1": false,
        "z2": false,
        "z3": false
    },
    {
        "name": "Raopura",
        "x1": false,
        "x2": false,
        "x3": false,
        "x4": false,
        "x5": false,
        "x6": false,
        "x7": false,
        "x8": false,
        "x9": false,
        "x10": false,
        "y1": false,
        "y2": false,
        "y3": false,
        "y4": false,
        "z1": false,
        "z2": false,
        "z3": false
    }
]
